semantha_streamlit_compare/__init__.py
semantha_streamlit_compare/components/__init__.py
semantha_streamlit_compare/components/compare.py
semantha_streamlit_compare/components/semantha.py
semantha_streamlit_compare-0.2.1.dist-info/METADATA
semantha_streamlit_compare-0.2.1.dist-info/WHEEL
semantha_streamlit_compare-0.2.1.dist-info/RECORD
