Metadata-Version: 2.1
Name: semantha-streamlit-compare
Version: 0.2.1
Summary: This is the project for a streamlit component which uses semantha semantic compare.
Author: thingsTHINKING GmbH
Author-email: github@thingsthinking.net
Requires-Python: >=3.10,<4.0
Classifier: Programming Language :: Python :: 3
Classifier: Programming Language :: Python :: 3.10
Classifier: Programming Language :: Python :: 3.11
Requires-Dist: requests (>=2.28.1,<3.0.0)
Requires-Dist: semantha_sdk (==4.2.0)
Requires-Dist: streamlit (>=1.14.0,<2.0.0)
